config/__init__.py
config/manager.py
data/__init__.py
data/manager.py
fire/__init__.py
fire/activity.py
fire/behavior.py
fire/effects.py
fire/fuel.py
fire/ignition.py
fire/laflammap_adapter.py
fire/mtt_numba.py
fire/simulation.py
fire/spatiotemporal_ignition.py
fire/visualization.py
laflammscape-0.1.5.dist-info/licenses/LICENSE
output/__init__.py
output/manager.py
simulation/__init__.py
simulation/orchestrator.py
state/__init__.py
state/representation.py
state/tracker.py
transition/module.py
weather/module.py
laflammscape-0.1.5.dist-info/METADATA
laflammscape-0.1.5.dist-info/WHEEL
laflammscape-0.1.5.dist-info/top_level.txt
laflammscape-0.1.5.dist-info/RECORD
