Metadata-Version: 2.4
Name: laflammscape
Version: 0.1.5
Summary: A short description of the laflammscape package.
Author-email: Your Name <you@example.com>
Project-URL: Homepage, https://github.com/yourusername/laflammscape
Project-URL: Bug Tracker, https://github.com/yourusername/laflammscape/issues
Classifier: Programming Language :: Python :: 3
Classifier: License :: OSI Approved :: MIT License
Classifier: Operating System :: OS Independent
Requires-Python: >=3.8
License-File: LICENSE
Dynamic: license-file
